Metadata-Version: 1.0
Name: bino-gauss-probab
Version: 1.1
Summary: Gaussian and Binomial distributions
Home-page: UNKNOWN
Author: Sreya Basak
Author-email: UNKNOWN
License: UNKNOWN
Platform: UNKNOWN
